{
  "iconTree": {
    "tag": "svg",
    "attr": {
      "viewBox": "0 0 24 24",
      "fill": "none",
      "stroke": "currentColor",
      "strokeWidth": "2",
      "strokeLinecap": "round",
      "strokeLinejoin": "round"
    },
    "child": [
      {
        "tag": "path",
        "attr": {
          "d": "m5.2 6.2 1.4 1.4"
        },
        "child": []
      },
      {
        "tag": "path",
        "attr": {
          "d": "M2 13h2"
        },
        "child": []
      },
      {
        "tag": "path",
        "attr": {
          "d": "M20 13h2"
        },
        "child": []
      },
      {
        "tag": "path",
        "attr": {
          "d": "m17.4 7.6 1.4-1.4"
        },
        "child": []
      },
      {
        "tag": "path",
        "attr": {
          "d": "M22 17H2"
        },
        "child": []
      },
      {
        "tag": "path",
        "attr": {
          "d": "M22 21H2"
        },
        "child": []
      },
      {
        "tag": "path",
        "attr": {
          "d": "M16 13a4 4 0 0 0-8 0"
        },
        "child": []
      },
      {
        "tag": "path",
        "attr": {
          "d": "M12 5V2.5"
        },
        "child": []
      }
    ]
  },
  "variant": "outlined"
}