{
  "iconTree": {
    "tag": "svg",
    "attr": {
      "viewBox": "0 0 24 24",
      "strokeWidth": "2",
      "stroke": "currentColor",
      "fill": "none",
      "strokeLinecap": "round",
      "strokeLinejoin": "round"
    },
    "child": [
      {
        "tag": "path",
        "attr": {
          "stroke": "none",
          "d": "M0 0h24v24H0z",
          "fill": "none"
        },
        "child": []
      },
      {
        "tag": "path",
        "attr": {
          "d": "M12 17v4"
        },
        "child": []
      },
      {
        "tag": "path",
        "attr": {
          "d": "M10 20l4 -2"
        },
        "child": []
      },
      {
        "tag": "path",
        "attr": {
          "d": "M10 18l4 2"
        },
        "child": []
      },
      {
        "tag": "path",
        "attr": {
          "d": "M5 17v4"
        },
        "child": []
      },
      {
        "tag": "path",
        "attr": {
          "d": "M3 20l4 -2"
        },
        "child": []
      },
      {
        "tag": "path",
        "attr": {
          "d": "M3 18l4 2"
        },
        "child": []
      },
      {
        "tag": "path",
        "attr": {
          "d": "M19 17v4"
        },
        "child": []
      },
      {
        "tag": "path",
        "attr": {
          "d": "M17 20l4 -2"
        },
        "child": []
      },
      {
        "tag": "path",
        "attr": {
          "d": "M17 18l4 2"
        },
        "child": []
      },
      {
        "tag": "path",
        "attr": {
          "d": "M7 14v-8a2 2 0 0 1 2 -2h6a2 2 0 0 1 2 2v8"
        },
        "child": []
      },
      {
        "tag": "path",
        "attr": {
          "d": "M11 5h2"
        },
        "child": []
      },
      {
        "tag": "path",
        "attr": {
          "d": "M12 17v.01"
        },
        "child": []
      }
    ]
  },
  "variant": "outlined"
}