{
  "iconTree": {
    "tag": "svg",
    "attr": {
      "viewBox": "0 0 24 24",
      "strokeWidth": "2",
      "stroke": "currentColor",
      "fill": "none",
      "strokeLinecap": "round",
      "strokeLinejoin": "round"
    },
    "child": [
      {
        "tag": "path",
        "attr": {
          "stroke": "none",
          "d": "M0 0h24v24H0z",
          "fill": "none"
        },
        "child": []
      },
      {
        "tag": "path",
        "attr": {
          "d": "M3.575 3.597a2 2 0 0 0 2.849 2.808"
        },
        "child": []
      },
      {
        "tag": "path",
        "attr": {
          "d": "M19 5m-2 0a2 2 0 1 0 4 0a2 2 0 1 0 -4 0"
        },
        "child": []
      },
      {
        "tag": "path",
        "attr": {
          "d": "M5 19m-2 0a2 2 0 1 0 4 0a2 2 0 1 0 -4 0"
        },
        "child": []
      },
      {
        "tag": "path",
        "attr": {
          "d": "M17.574 17.598a2 2 0 0 0 2.826 2.83"
        },
        "child": []
      },
      {
        "tag": "path",
        "attr": {
          "d": "M5 7v10"
        },
        "child": []
      },
      {
        "tag": "path",
        "attr": {
          "d": "M9 5h8"
        },
        "child": []
      },
      {
        "tag": "path",
        "attr": {
          "d": "M7 19h10"
        },
        "child": []
      },
      {
        "tag": "path",
        "attr": {
          "d": "M19 7v8"
        },
        "child": []
      },
      {
        "tag": "path",
        "attr": {
          "d": "M3 3l18 18"
        },
        "child": []
      }
    ]
  },
  "variant": "outlined"
}