{
  "iconTree": {
    "tag": "svg",
    "attr": {
      "viewBox": "0 0 24 24",
      "fill": "none",
      "stroke": "currentColor"
    },
    "child": [
      {
        "tag": "path",
        "attr": {
          "d": "M9 11H15V13H9V11Z",
          "strokeOpacity": "0.5",
          "strokeWidth": "2"
        },
        "child": []
      },
      {
        "tag": "path",
        "attr": {
          "d": "M19 7H5V5H19V7Z"
        },
        "child": []
      },
      {
        "tag": "path",
        "attr": {
          "d": "M19 19H5V17H19V19Z"
        },
        "child": []
      }
    ]
  },
  "variant": "full"
}